[
  {
    "window": 1,
    "train_start": "2023-07-19",
    "train_end": "2023-10-18",
    "test_start": "2023-10-19",
    "test_end": "2023-11-17",
    "auc": 0.999991306464513,
    "top_features": [
      {
        "feature": "volume_ratio_ma50",
        "importance": 0.24048572778701782
      },
      {
        "feature": "momentum_20d",
        "importance": 0.09133195877075195
      },
      {
        "feature": "volume_ratio_ma20",
        "importance": 0.07398127019405365
      },
      {
        "feature": "grade_numeric",
        "importance": 0.04035723954439163
      },
      {
        "feature": "total_net_sum_20d",
        "importance": 0.038926996290683746
      },
      {
        "feature": "total_net_lag1",
        "importance": 0.037291985005140305
      },
      {
        "feature": "risk_pct",
        "importance": 0.03623626008629799
      },
      {
        "feature": "volume_trend_5d",
        "importance": 0.03355243429541588
      },
      {
        "feature": "rsi_14",
        "importance": 0.03263052925467491
      },
      {
        "feature": "foreign_net_sum_5d",
        "importance": 0.030122697353363037
      }
    ]
  },
  {
    "window": 2,
    "train_start": "2023-08-21",
    "train_end": "2023-11-17",
    "test_start": "2023-11-20",
    "test_end": "2023-12-18",
    "auc": 0.996258427454118,
    "top_features": [
      {
        "feature": "volume_ratio_ma50",
        "importance": 0.14321966469287872
      },
      {
        "feature": "momentum_20d",
        "importance": 0.06912290304899216
      },
      {
        "feature": "total_net_sum_3d",
        "importance": 0.04571482166647911
      },
      {
        "feature": "foreign_net_sum_20d",
        "importance": 0.043870918452739716
      },
      {
        "feature": "foreign_net_lag1",
        "importance": 0.039465416222810745
      },
      {
        "feature": "total_net_sum_20d",
        "importance": 0.038016993552446365
      },
      {
        "feature": "risk_pct",
        "importance": 0.03797012194991112
      },
      {
        "feature": "volume_ratio_ma20",
        "importance": 0.03756892681121826
      },
      {
        "feature": "foreign_net_sum_5d",
        "importance": 0.03717152401804924
      },
      {
        "feature": "distance_to_buy_pct",
        "importance": 0.035827185958623886
      }
    ]
  },
  {
    "window": 3,
    "train_start": "2023-09-19",
    "train_end": "2023-12-18",
    "test_start": "2023-12-19",
    "test_end": "2024-01-18",
    "auc": 0.9746254875208445,
    "top_features": [
      {
        "feature": "volume_ratio_ma50",
        "importance": 0.05910203605890274
      },
      {
        "feature": "momentum_20d",
        "importance": 0.055593959987163544
      },
      {
        "feature": "total_net_sum_10d",
        "importance": 0.046116653829813004
      },
      {
        "feature": "rsi_14",
        "importance": 0.044781118631362915
      },
      {
        "feature": "dealer_net_lag1",
        "importance": 0.04412980377674103
      },
      {
        "feature": "risk_pct",
        "importance": 0.04401408135890961
      },
      {
        "feature": "total_net_sum_3d",
        "importance": 0.04386913403868675
      },
      {
        "feature": "investment_net_lag1",
        "importance": 0.043096303939819336
      },
      {
        "feature": "distance_to_buy_pct",
        "importance": 0.042708802968263626
      },
      {
        "feature": "total_net_sum_20d",
        "importance": 0.040420856326818466
      }
    ]
  },
  {
    "window": 4,
    "train_start": "2023-10-19",
    "train_end": "2024-01-18",
    "test_start": "2024-01-19",
    "test_end": "2024-02-16",
    "auc": 0.9870077593081028,
    "top_features": [
      {
        "feature": "momentum_5d",
        "importance": 0.06966640055179596
      },
      {
        "feature": "volume_surge",
        "importance": 0.05494727939367294
      },
      {
        "feature": "distance_to_buy_pct",
        "importance": 0.05222772806882858
      },
      {
        "feature": "foreign_net_sum_20d",
        "importance": 0.04600085690617561
      },
      {
        "feature": "total_net_sum_20d",
        "importance": 0.04448992758989334
      },
      {
        "feature": "total_net_sum_3d",
        "importance": 0.04234180599451065
      },
      {
        "feature": "volume_ratio_ma50",
        "importance": 0.04139912128448486
      },
      {
        "feature": "risk_pct",
        "importance": 0.04137035086750984
      },
      {
        "feature": "total_net_lag1",
        "importance": 0.03875918686389923
      },
      {
        "feature": "rsi_14",
        "importance": 0.038201384246349335
      }
    ]
  },
  {
    "window": 5,
    "train_start": "2023-11-20",
    "train_end": "2024-02-16",
    "test_start": "2024-02-19",
    "test_end": "2024-03-18",
    "auc": 0.9858340904887875,
    "top_features": [
      {
        "feature": "grade_numeric",
        "importance": 0.06312745809555054
      },
      {
        "feature": "risk_pct",
        "importance": 0.060308244079351425
      },
      {
        "feature": "total_net_sum_10d",
        "importance": 0.04954471439123154
      },
      {
        "feature": "momentum_20d",
        "importance": 0.04859648644924164
      },
      {
        "feature": "momentum_5d",
        "importance": 0.04458927363157272
      },
      {
        "feature": "total_net_sum_5d",
        "importance": 0.04180589318275452
      },
      {
        "feature": "total_net_sum_20d",
        "importance": 0.04153163731098175
      },
      {
        "feature": "foreign_net_sum_20d",
        "importance": 0.04115717485547066
      },
      {
        "feature": "foreign_investment_spread_lag1",
        "importance": 0.040972065180540085
      },
      {
        "feature": "foreign_net_lag1",
        "importance": 0.040862634778022766
      }
    ]
  },
  {
    "window": 6,
    "train_start": "2023-12-19",
    "train_end": "2024-03-18",
    "test_start": "2024-03-19",
    "test_end": "2024-04-18",
    "auc": 0.9872268212504498,
    "top_features": [
      {
        "feature": "risk_pct",
        "importance": 0.05960850045084953
      },
      {
        "feature": "volume_ratio_ma50",
        "importance": 0.055205538868904114
      },
      {
        "feature": "foreign_net_sum_10d",
        "importance": 0.050646014511585236
      },
      {
        "feature": "total_net_sum_5d",
        "importance": 0.04991225153207779
      },
      {
        "feature": "foreign_net_sum_20d",
        "importance": 0.04864409193396568
      },
      {
        "feature": "volume_trend_5d",
        "importance": 0.04703107848763466
      },
      {
        "feature": "total_net_sum_20d",
        "importance": 0.04454820975661278
      },
      {
        "feature": "momentum_20d",
        "importance": 0.04427430406212807
      },
      {
        "feature": "total_net_sum_3d",
        "importance": 0.04250723868608475
      },
      {
        "feature": "foreign_net_sum_5d",
        "importance": 0.03867293894290924
      }
    ]
  },
  {
    "window": 7,
    "train_start": "2024-01-19",
    "train_end": "2024-04-18",
    "test_start": "2024-04-19",
    "test_end": "2024-05-17",
    "auc": 0.9965497323189632,
    "top_features": [
      {
        "feature": "volume_ratio_ma20",
        "importance": 0.05325951799750328
      },
      {
        "feature": "total_net_sum_5d",
        "importance": 0.04845067486166954
      },
      {
        "feature": "total_net_sum_20d",
        "importance": 0.04771151766180992
      },
      {
        "feature": "foreign_net_sum_10d",
        "importance": 0.044492390006780624
      },
      {
        "feature": "volume_ratio_ma50",
        "importance": 0.04354318603873253
      },
      {
        "feature": "momentum_20d",
        "importance": 0.04349539801478386
      },
      {
        "feature": "total_net_sum_3d",
        "importance": 0.04261069372296333
      },
      {
        "feature": "foreign_net_sum_20d",
        "importance": 0.042140763252973557
      },
      {
        "feature": "investment_net_lag1",
        "importance": 0.04144706949591637
      },
      {
        "feature": "risk_pct",
        "importance": 0.0413031242787838
      }
    ]
  },
  {
    "window": 8,
    "train_start": "2024-02-19",
    "train_end": "2024-05-17",
    "test_start": "2024-05-20",
    "test_end": "2024-06-18",
    "auc": 0.9860595612344927,
    "top_features": [
      {
        "feature": "risk_pct",
        "importance": 0.06468784064054489
      },
      {
        "feature": "total_net_sum_5d",
        "importance": 0.05535684898495674
      },
      {
        "feature": "foreign_net_sum_20d",
        "importance": 0.04811965674161911
      },
      {
        "feature": "total_net_sum_3d",
        "importance": 0.04582047462463379
      },
      {
        "feature": "total_net_sum_20d",
        "importance": 0.04320968687534332
      },
      {
        "feature": "dealer_net_lag1",
        "importance": 0.042830001562833786
      },
      {
        "feature": "momentum_20d",
        "importance": 0.04183775931596756
      },
      {
        "feature": "volume_ratio_ma50",
        "importance": 0.040839217603206635
      },
      {
        "feature": "total_net_sum_10d",
        "importance": 0.040586914867162704
      },
      {
        "feature": "foreign_investment_spread_lag1",
        "importance": 0.04042622819542885
      }
    ]
  },
  {
    "window": 9,
    "train_start": "2024-03-19",
    "train_end": "2024-06-18",
    "test_start": "2024-06-19",
    "test_end": "2024-07-18",
    "auc": 0.9662437663109481,
    "top_features": [
      {
        "feature": "risk_pct",
        "importance": 0.05619218200445175
      },
      {
        "feature": "volume_trend_5d",
        "importance": 0.05525927618145943
      },
      {
        "feature": "foreign_net_sum_20d",
        "importance": 0.04829896613955498
      },
      {
        "feature": "total_net_sum_20d",
        "importance": 0.04657639190554619
      },
      {
        "feature": "volume_ratio_ma20",
        "importance": 0.04622858762741089
      },
      {
        "feature": "grade_numeric",
        "importance": 0.045138902962207794
      },
      {
        "feature": "foreign_investment_spread_lag1",
        "importance": 0.04393308237195015
      },
      {
        "feature": "momentum_20d",
        "importance": 0.04375676438212395
      },
      {
        "feature": "volume_ratio_ma50",
        "importance": 0.04279479756951332
      },
      {
        "feature": "total_net_sum_5d",
        "importance": 0.04251695051789284
      }
    ]
  },
  {
    "window": 10,
    "train_start": "2024-04-19",
    "train_end": "2024-07-18",
    "test_start": "2024-07-19",
    "test_end": "2024-08-16",
    "auc": 0.9856137139464701,
    "top_features": [
      {
        "feature": "grade_numeric",
        "importance": 0.14334096014499664
      },
      {
        "feature": "distance_to_buy_pct",
        "importance": 0.07350684702396393
      },
      {
        "feature": "total_net_sum_20d",
        "importance": 0.045343492180109024
      },
      {
        "feature": "rsi_14",
        "importance": 0.04417520761489868
      },
      {
        "feature": "risk_pct",
        "importance": 0.04322745278477669
      },
      {
        "feature": "volume_ratio_ma50",
        "importance": 0.043144334107637405
      },
      {
        "feature": "foreign_net_sum_20d",
        "importance": 0.04201974347233772
      },
      {
        "feature": "dealer_dominance_lag1",
        "importance": 0.038793500512838364
      },
      {
        "feature": "total_net_sum_3d",
        "importance": 0.03846663609147072
      },
      {
        "feature": "total_net_sum_5d",
        "importance": 0.037284333258867264
      }
    ]
  },
  {
    "window": 11,
    "train_start": "2024-05-20",
    "train_end": "2024-08-16",
    "test_start": "2024-08-19",
    "test_end": "2024-09-18",
    "auc": 0.9903861719349066,
    "top_features": [
      {
        "feature": "total_net_sum_20d",
        "importance": 0.05594344809651375
      },
      {
        "feature": "total_net_sum_10d",
        "importance": 0.047650814056396484
      },
      {
        "feature": "volume_ratio_ma50",
        "importance": 0.04682409390807152
      },
      {
        "feature": "volume_ratio_ma20",
        "importance": 0.046614330261945724
      },
      {
        "feature": "momentum_20d",
        "importance": 0.04394393414258957
      },
      {
        "feature": "rsi_14",
        "importance": 0.043652456253767014
      },
      {
        "feature": "foreign_net_sum_10d",
        "importance": 0.04211512953042984
      },
      {
        "feature": "momentum_5d",
        "importance": 0.04165760427713394
      },
      {
        "feature": "grade_numeric",
        "importance": 0.04148022085428238
      },
      {
        "feature": "total_net_to_vol_lag1",
        "importance": 0.04062581807374954
      }
    ]
  },
  {
    "window": 12,
    "train_start": "2024-06-19",
    "train_end": "2024-09-18",
    "test_start": "2024-09-19",
    "test_end": "2024-10-18",
    "auc": 0.9822055445879199,
    "top_features": [
      {
        "feature": "foreign_investment_spread_lag1",
        "importance": 0.05809687077999115
      },
      {
        "feature": "total_net_sum_20d",
        "importance": 0.05349805951118469
      },
      {
        "feature": "risk_pct",
        "importance": 0.05343829467892647
      },
      {
        "feature": "foreign_net_sum_20d",
        "importance": 0.04946150258183479
      },
      {
        "feature": "rsi_14",
        "importance": 0.0489669032394886
      },
      {
        "feature": "dealer_net_lag1",
        "importance": 0.046739380806684494
      },
      {
        "feature": "foreign_net_sum_5d",
        "importance": 0.04665512591600418
      },
      {
        "feature": "total_net_sum_5d",
        "importance": 0.04389941692352295
      },
      {
        "feature": "grade_numeric",
        "importance": 0.04300603270530701
      },
      {
        "feature": "investment_net_lag1",
        "importance": 0.03855092450976372
      }
    ]
  },
  {
    "window": 13,
    "train_start": "2024-07-19",
    "train_end": "2024-10-18",
    "test_start": "2024-10-21",
    "test_end": "2024-11-18",
    "auc": 0.9876872869297835,
    "top_features": [
      {
        "feature": "grade_numeric",
        "importance": 0.09586121141910553
      },
      {
        "feature": "dealer_net_lag1",
        "importance": 0.05795824155211449
      },
      {
        "feature": "distance_to_buy_pct",
        "importance": 0.04891414940357208
      },
      {
        "feature": "investment_net_lag1",
        "importance": 0.046600569039583206
      },
      {
        "feature": "risk_pct",
        "importance": 0.042477089911699295
      },
      {
        "feature": "total_net_to_vol_lag1",
        "importance": 0.0404890701174736
      },
      {
        "feature": "total_net_sum_20d",
        "importance": 0.04030448943376541
      },
      {
        "feature": "rsi_14",
        "importance": 0.03973107039928436
      },
      {
        "feature": "dealer_dominance_lag1",
        "importance": 0.039412640035152435
      },
      {
        "feature": "volume_ratio_ma50",
        "importance": 0.039252568036317825
      }
    ]
  },
  {
    "window": 14,
    "train_start": "2024-08-19",
    "train_end": "2024-11-18",
    "test_start": "2024-11-19",
    "test_end": "2024-12-18",
    "auc": 0.9889042242658543,
    "top_features": [
      {
        "feature": "total_net_sum_20d",
        "importance": 0.050301991403102875
      },
      {
        "feature": "foreign_investment_spread_lag1",
        "importance": 0.04969774931669235
      },
      {
        "feature": "dealer_net_lag1",
        "importance": 0.048175882548093796
      },
      {
        "feature": "momentum_20d",
        "importance": 0.04743242636322975
      },
      {
        "feature": "total_net_sum_10d",
        "importance": 0.04587051644921303
      },
      {
        "feature": "foreign_net_sum_20d",
        "importance": 0.04531770572066307
      },
      {
        "feature": "risk_pct",
        "importance": 0.04508921504020691
      },
      {
        "feature": "investment_net_lag1",
        "importance": 0.043940138071775436
      },
      {
        "feature": "rsi_14",
        "importance": 0.04308144003152847
      },
      {
        "feature": "foreign_net_lag1",
        "importance": 0.04226714000105858
      }
    ]
  },
  {
    "window": 15,
    "train_start": "2024-09-19",
    "train_end": "2024-12-18",
    "test_start": "2024-12-19",
    "test_end": "2025-01-17",
    "auc": 0.992516216562438,
    "top_features": [
      {
        "feature": "foreign_net_sum_10d",
        "importance": 0.050919849425554276
      },
      {
        "feature": "volume_trend_5d",
        "importance": 0.04834476858377457
      },
      {
        "feature": "total_net_sum_20d",
        "importance": 0.04555441066622734
      },
      {
        "feature": "investment_net_lag1",
        "importance": 0.04522300139069557
      },
      {
        "feature": "distance_to_buy_pct",
        "importance": 0.04471524432301521
      },
      {
        "feature": "momentum_20d",
        "importance": 0.04414648935198784
      },
      {
        "feature": "rsi_14",
        "importance": 0.04314765706658363
      },
      {
        "feature": "total_net_sum_10d",
        "importance": 0.04250146448612213
      },
      {
        "feature": "foreign_net_sum_20d",
        "importance": 0.04098675027489662
      },
      {
        "feature": "volume_ratio_ma20",
        "importance": 0.0405835397541523
      }
    ]
  },
  {
    "window": 16,
    "train_start": "2024-10-21",
    "train_end": "2025-01-17",
    "test_start": "2025-01-20",
    "test_end": "2025-02-18",
    "auc": 0.9987195902688859,
    "top_features": [
      {
        "feature": "rsi_14",
        "importance": 0.06080790236592293
      },
      {
        "feature": "risk_pct",
        "importance": 0.054431937634944916
      },
      {
        "feature": "total_net_sum_3d",
        "importance": 0.053487833589315414
      },
      {
        "feature": "total_net_sum_10d",
        "importance": 0.05325331538915634
      },
      {
        "feature": "foreign_net_sum_5d",
        "importance": 0.04774906113743782
      },
      {
        "feature": "total_net_sum_20d",
        "importance": 0.04659341648221016
      },
      {
        "feature": "foreign_net_sum_3d",
        "importance": 0.04583160579204559
      },
      {
        "feature": "momentum_20d",
        "importance": 0.04571610689163208
      },
      {
        "feature": "foreign_net_sum_10d",
        "importance": 0.04487059637904167
      },
      {
        "feature": "investment_net_lag1",
        "importance": 0.04474171996116638
      }
    ]
  },
  {
    "window": 17,
    "train_start": "2024-11-19",
    "train_end": "2025-02-18",
    "test_start": "2025-02-19",
    "test_end": "2025-03-18",
    "auc": 0.999283231972198,
    "top_features": [
      {
        "feature": "dealer_net_lag1",
        "importance": 0.08622010797262192
      },
      {
        "feature": "total_net_sum_20d",
        "importance": 0.05969022586941719
      },
      {
        "feature": "total_net_sum_5d",
        "importance": 0.055018164217472076
      },
      {
        "feature": "total_net_sum_10d",
        "importance": 0.05405097082257271
      },
      {
        "feature": "risk_pct",
        "importance": 0.05242070183157921
      },
      {
        "feature": "volume_surge",
        "importance": 0.042818814516067505
      },
      {
        "feature": "foreign_net_sum_3d",
        "importance": 0.04235869273543358
      },
      {
        "feature": "foreign_net_sum_20d",
        "importance": 0.04011388495564461
      },
      {
        "feature": "rsi_14",
        "importance": 0.040053579956293106
      },
      {
        "feature": "foreign_net_sum_10d",
        "importance": 0.03852264955639839
      }
    ]
  },
  {
    "window": 18,
    "train_start": "2024-12-19",
    "train_end": "2025-03-18",
    "test_start": "2025-03-19",
    "test_end": "2025-04-18",
    "auc": 1.0,
    "top_features": [
      {
        "feature": "total_net_sum_10d",
        "importance": 0.09273989498615265
      },
      {
        "feature": "foreign_net_sum_20d",
        "importance": 0.0696214810013771
      },
      {
        "feature": "foreign_net_sum_10d",
        "importance": 0.05191434174776077
      },
      {
        "feature": "foreign_investment_spread_lag1",
        "importance": 0.05121481046080589
      },
      {
        "feature": "foreign_net_sum_3d",
        "importance": 0.04983040317893028
      },
      {
        "feature": "foreign_net_sum_5d",
        "importance": 0.04959231987595558
      },
      {
        "feature": "momentum_20d",
        "importance": 0.048026591539382935
      },
      {
        "feature": "volume_ratio_ma50",
        "importance": 0.0467521958053112
      },
      {
        "feature": "momentum_5d",
        "importance": 0.04491138458251953
      },
      {
        "feature": "total_net_sum_5d",
        "importance": 0.04226238280534744
      }
    ]
  },
  {
    "window": 19,
    "train_start": "2025-01-20",
    "train_end": "2025-04-18",
    "test_start": "2025-04-21",
    "test_end": "2025-05-16",
    "auc": 1.0,
    "top_features": [
      {
        "feature": "total_net_sum_5d",
        "importance": 0.13938790559768677
      },
      {
        "feature": "risk_pct",
        "importance": 0.08527949452400208
      },
      {
        "feature": "foreign_net_sum_20d",
        "importance": 0.06687383353710175
      },
      {
        "feature": "volume_ratio_ma50",
        "importance": 0.06407878547906876
      },
      {
        "feature": "distance_to_buy_pct",
        "importance": 0.06133163720369339
      },
      {
        "feature": "foreign_net_sum_5d",
        "importance": 0.059702783823013306
      },
      {
        "feature": "momentum_5d",
        "importance": 0.05013705790042877
      },
      {
        "feature": "foreign_net_sum_10d",
        "importance": 0.049969084560871124
      },
      {
        "feature": "total_net_sum_10d",
        "importance": 0.0459066741168499
      },
      {
        "feature": "momentum_20d",
        "importance": 0.04482360556721687
      }
    ]
  },
  {
    "window": 20,
    "train_start": "2025-02-19",
    "train_end": "2025-05-16",
    "test_start": "2025-05-19",
    "test_end": "2025-06-18",
    "auc": 0.9996477881093266,
    "top_features": [
      {
        "feature": "total_net_sum_3d",
        "importance": 0.06440895795822144
      },
      {
        "feature": "foreign_net_sum_20d",
        "importance": 0.06369328498840332
      },
      {
        "feature": "total_net_sum_10d",
        "importance": 0.05818605422973633
      },
      {
        "feature": "total_net_sum_5d",
        "importance": 0.05079839378595352
      },
      {
        "feature": "grade_numeric",
        "importance": 0.04948044940829277
      },
      {
        "feature": "risk_pct",
        "importance": 0.045487456023693085
      },
      {
        "feature": "investment_net_lag1",
        "importance": 0.043920304626226425
      },
      {
        "feature": "total_net_sum_20d",
        "importance": 0.04387445002794266
      },
      {
        "feature": "volume_ratio_ma50",
        "importance": 0.043343447148799896
      },
      {
        "feature": "rsi_14",
        "importance": 0.04150755703449249
      }
    ]
  },
  {
    "window": 21,
    "train_start": "2025-03-19",
    "train_end": "2025-06-18",
    "test_start": "2025-06-19",
    "test_end": "2025-07-18",
    "auc": 0.9996196479026299,
    "top_features": [
      {
        "feature": "grade_numeric",
        "importance": 0.0829717144370079
      },
      {
        "feature": "total_net_sum_10d",
        "importance": 0.07818630337715149
      },
      {
        "feature": "total_net_sum_5d",
        "importance": 0.054842233657836914
      },
      {
        "feature": "total_net_sum_20d",
        "importance": 0.05330386385321617
      },
      {
        "feature": "rsi_14",
        "importance": 0.05046970024704933
      },
      {
        "feature": "risk_pct",
        "importance": 0.049066975712776184
      },
      {
        "feature": "foreign_net_sum_20d",
        "importance": 0.04756128415465355
      },
      {
        "feature": "foreign_net_sum_5d",
        "importance": 0.04246973991394043
      },
      {
        "feature": "foreign_net_sum_3d",
        "importance": 0.04229708015918732
      },
      {
        "feature": "total_net_sum_3d",
        "importance": 0.04176725819706917
      }
    ]
  },
  {
    "window": 22,
    "train_start": "2025-04-21",
    "train_end": "2025-07-18",
    "test_start": "2025-07-21",
    "test_end": "2025-08-18",
    "auc": 0.9968867030636647,
    "top_features": [
      {
        "feature": "rsi_14",
        "importance": 0.06770417094230652
      },
      {
        "feature": "dealer_dominance_lag1",
        "importance": 0.0524500347673893
      },
      {
        "feature": "foreign_investment_spread_lag1",
        "importance": 0.049294520169496536
      },
      {
        "feature": "foreign_net_sum_20d",
        "importance": 0.04886176437139511
      },
      {
        "feature": "foreign_net_sum_10d",
        "importance": 0.047970548272132874
      },
      {
        "feature": "investment_net_lag1",
        "importance": 0.047268129885196686
      },
      {
        "feature": "volume_ratio_ma50",
        "importance": 0.04565112292766571
      },
      {
        "feature": "volume_ratio_ma20",
        "importance": 0.04450284317135811
      },
      {
        "feature": "total_net_to_vol_lag1",
        "importance": 0.042402349412441254
      },
      {
        "feature": "total_net_sum_10d",
        "importance": 0.04217883199453354
      }
    ]
  },
  {
    "window": 23,
    "train_start": "2025-05-19",
    "train_end": "2025-08-18",
    "test_start": "2025-08-19",
    "test_end": "2025-09-18",
    "auc": 0.9970177947305316,
    "top_features": [
      {
        "feature": "grade_numeric",
        "importance": 0.11480879038572311
      },
      {
        "feature": "momentum_20d",
        "importance": 0.05956212803721428
      },
      {
        "feature": "investment_net_lag1",
        "importance": 0.05662352219223976
      },
      {
        "feature": "foreign_net_sum_20d",
        "importance": 0.05204186588525772
      },
      {
        "feature": "momentum_5d",
        "importance": 0.04998095706105232
      },
      {
        "feature": "total_net_sum_5d",
        "importance": 0.04927234351634979
      },
      {
        "feature": "rsi_14",
        "importance": 0.04558094963431358
      },
      {
        "feature": "volume_ratio_ma20",
        "importance": 0.0389840342104435
      },
      {
        "feature": "total_net_sum_20d",
        "importance": 0.038025129586458206
      },
      {
        "feature": "total_net_sum_10d",
        "importance": 0.03581102564930916
      }
    ]
  },
  {
    "window": 24,
    "train_start": "2025-06-19",
    "train_end": "2025-09-18",
    "test_start": "2025-09-19",
    "test_end": "2025-10-17",
    "auc": 0.998109640831758,
    "top_features": [
      {
        "feature": "total_net_sum_10d",
        "importance": 0.06272175908088684
      },
      {
        "feature": "foreign_investment_spread_lag1",
        "importance": 0.05645152926445007
      },
      {
        "feature": "momentum_20d",
        "importance": 0.052818287163972855
      },
      {
        "feature": "foreign_net_sum_20d",
        "importance": 0.05155685171484947
      },
      {
        "feature": "investment_net_lag1",
        "importance": 0.04913904145359993
      },
      {
        "feature": "rsi_14",
        "importance": 0.049076423048973083
      },
      {
        "feature": "total_net_sum_20d",
        "importance": 0.04897726699709892
      },
      {
        "feature": "risk_pct",
        "importance": 0.048570431768894196
      },
      {
        "feature": "distance_to_buy_pct",
        "importance": 0.04473171383142471
      },
      {
        "feature": "volume_ratio_ma50",
        "importance": 0.04443252459168434
      }
    ]
  }
]